elements/__init__.py
elements/classes.py
elements/elements.py
elements/lists.py
tests/__init__.py
tests/test_classes.py
tests/test_elements_dict.py
tests/test_elements_integration.py
tests/test_lists.py
elemenpy-1.2.0.dist-info/LICENSE
elemenpy-1.2.0.dist-info/METADATA
elemenpy-1.2.0.dist-info/WHEEL
elemenpy-1.2.0.dist-info/top_level.txt
elemenpy-1.2.0.dist-info/RECORD
