Metadata-Version: 2.1
Name: elemenpy
Version: 1.2.0
Summary: A simple library for displaying an element's properties.
Home-page: https://github.com/import-brain/elements.py
Author: Eric Cheng
Author-email: ericcheng9316@gmail.com
License: MIT License
Platform: UNKNOWN
License-File: LICENSE
Requires-Dist: elements-py
